examples/__init__.py
examples/flask_app/__init__.py
examples/flask_app/app.py
examples/flask_app/config.py
examples/flask_app/tests/__init__.py
examples/flask_app/tests/conftest.py
examples/flask_app/tests/test_flask_app.py
flask_jwt_oidc/__init__.py
flask_jwt_oidc/exceptions.py
flask_jwt_oidc/jwt_manager.py
flask_jwt_oidc_mds/__init__.py
flask_jwt_oidc_mds/exceptions.py
flask_jwt_oidc_mds/jwt_manager.py
tests/__init__.py
tests/conftest.py
tests/test_cookie_protected.py
tests/test_protected.py
tests/test_unprotected.py
flask_jwt_oidc_mds-0.0.3.dist-info/LICENSE
flask_jwt_oidc_mds-0.0.3.dist-info/METADATA
flask_jwt_oidc_mds-0.0.3.dist-info/WHEEL
flask_jwt_oidc_mds-0.0.3.dist-info/top_level.txt
flask_jwt_oidc_mds-0.0.3.dist-info/RECORD
