Metadata-Version: 2.1
Name: flask-jwt-oidc-mds
Version: 0.0.3
Summary: Flask JWT OIDC MDS
Home-page: https://github.com/bcgov/flask-jwt-oidc
Author: mds devs, with help from others
Author-email: mds-devs@gov.bc.ca
License: Copyright 2018 Thor Wolpert        
Keywords: flask extension development
Platform: any
Classifier: Topic :: System :: Software Distribution
License-File: LICENSE
Requires-Dist: flask
Requires-Dist: cachelib
Requires-Dist: python-jose
Requires-Dist: six
